grpipe/__init__.py
grpipe/argument.py
grpipe/base.py
grpipe/cache.py
grpipe/pipeline.py
grpipe/step.py
grpipe/utils.py
grpipe-0.0.4.dist-info/LICENSE
grpipe-0.0.4.dist-info/METADATA
grpipe-0.0.4.dist-info/WHEEL
grpipe-0.0.4.dist-info/top_level.txt
grpipe-0.0.4.dist-info/RECORD
