Metadata-Version: 2.1
Name: grpipe
Version: 0.0.4
Summary: Computation pipelines with non-linear dependency graphs
Author-email: Dominik Schröder <schroeder.dominik@gmail.com>
Project-URL: Homepage, https://wirhabenzeit.github.io/grpipe/
Project-URL: Repository, https://github.com/wirhabenzeit/grpipe
Project-URL: Documentation, https://wirhabenzeit.github.io/grpipe/
Keywords: python
Classifier: Intended Audience :: Developers
Classifier: Programming Language :: Python
Classifier: Programming Language :: Python :: 3
Classifier: Programming Language :: Python :: 3.10
Classifier: Programming Language :: Python :: 3.11
Classifier: Programming Language :: Python :: 3.12
Classifier: Topic :: Software Development :: Libraries :: Python Modules
Requires-Python: <3.13,>=3.10
License-File: LICENSE
Requires-Dist: frozendict>=2.4.6
Requires-Dist: networkx>=3.2.1
Requires-Dist: polars
Requires-Dist: numpy>=2.0.2
Requires-Dist: xxhash>=3.5.0
Requires-Dist: pandas>=2.2.3
Requires-Dist: marimo>=0.9.10
